>   public net.minecraft.client.gui.screens.inventory.AbstractRecipeBookScreen(T, net.minecraft.client.gui.screens.recipebook.RecipeBookComponent<?>, net.minecraft.world.entity.player.Inventory, net.minecraft.network.chat.Component);
      Code:
         0: aload_0
         1: aload_1
         2: aload_3
         3: aload         4
         5: invokespecial #1                  // Method net/minecraft/client/gui/screens/inventory/AbstractContainerScreen."<init>":(Lnet/minecraft/world/inventory/AbstractContainerMenu;Lnet/minecraft/world/entity/player/Inventory;Lnet/minecraft/network/chat/Component;)V
         8: aload_0
         9: aload_2
>       10: putfield      #7                  // Field recipeBookComponent:Lnet/minecraft/client/gui/screens/recipebook/RecipeBookComponent;
        13: return
  
    protected void init();
      Code:
         0: aload_0
         1: invokespecial #13                 // Method net/minecraft/client/gui/screens/inventory/AbstractContainerScreen.init:()V
         4: aload_0
         5: aload_0
>       24: getfield      #7                  // Field recipeBookComponent:Lnet/minecraft/client/gui/screens/recipebook/RecipeBookComponent;
        27: aload_0
        28: getfield      #17                 // Field width:I
        31: aload_0
        32: getfield      #25                 // Field height:I
        35: aload_0
        36: getfield      #28                 // Field minecraft:Lnet/minecraft/client/Minecraft;
        39: aload_0
        40: getfield      #21                 // Field widthTooNarrow:Z
>       43: invokevirtual #32                 // Method net/minecraft/client/gui/screens/recipebook/RecipeBookComponent.init:(IILnet/minecraft/client/Minecraft;Z)V
        46: aload_0
        47: aload_0
>       48: getfield      #7                  // Field recipeBookComponent:Lnet/minecraft/client/gui/screens/recipebook/RecipeBookComponent;
        51: aload_0
        52: getfield      #17                 // Field width:I
        55: aload_0
        56: getfield      #37                 // Field imageWidth:I
>       59: invokevirtual #40                 // Method net/minecraft/client/gui/screens/recipebook/RecipeBookComponent.updateScreenPosition:(II)I
>       62: putfield      #44                 // Field leftPos:I
        65: aload_0
        66: invokevirtual #47                 // Method initButton:()V
        69: return
  
>   protected abstract net.minecraft.client.gui.navigation.ScreenPosition getRecipeBookButtonPosition();
  
    protected void onRecipeBookButtonClick();
      Code:
         0: return
  
>   public void extractRenderState(net.minecraft.client.gui.GuiGraphicsExtractor, int, int, float);
      Code:
         0: aload_0
>        1: getfield      #7                  // Field recipeBookComponent:Lnet/minecraft/client/gui/screens/recipebook/RecipeBookComponent;
>        4: invokevirtual #83                 // Method net/minecraft/client/gui/screens/recipebook/RecipeBookComponent.isVisible:()Z
         7: ifeq          29
        10: aload_0
        11: getfield      #21                 // Field widthTooNarrow:Z
        14: ifeq          29
        17: aload_0
        18: aload_1
        19: iload_2
        20: iload_3
>       43: getfield      #7                  // Field recipeBookComponent:Lnet/minecraft/client/gui/screens/recipebook/RecipeBookComponent;
        46: aload_1
        47: iload_2
        48: iload_3
        49: fload         4
>       51: invokevirtual #99                 // Method net/minecraft/client/gui/screens/recipebook/RecipeBookComponent.extractRenderState:(Lnet/minecraft/client/gui/GuiGraphicsExtractor;IIF)V
        54: aload_1
        55: invokevirtual #94                 // Method net/minecraft/client/gui/GuiGraphicsExtractor.nextStratum:()V
        58: aload_0
        59: aload_1
        60: iload_2
        61: iload_3
        62: invokevirtual #102                // Method extractCarriedItem:(Lnet/minecraft/client/gui/GuiGraphicsExtractor;II)V
        65: aload_0
>       78: getfield      #7                  // Field recipeBookComponent:Lnet/minecraft/client/gui/screens/recipebook/RecipeBookComponent;
        81: aload_1
        82: iload_2
        83: iload_3
        84: aload_0
        85: getfield      #113                // Field hoveredSlot:Lnet/minecraft/world/inventory/Slot;
>       88: invokevirtual #117                // Method net/minecraft/client/gui/screens/recipebook/RecipeBookComponent.extractTooltip:(Lnet/minecraft/client/gui/GuiGraphicsExtractor;IILnet/minecraft/world/inventory/Slot;)V
        91: return
  
    protected void extractSlots(net.minecraft.client.gui.GuiGraphicsExtractor, int, int);
      Code:
         0: aload_0
         1: aload_1
         2: iload_2
         3: iload_3
>        8: getfield      #7                  // Field recipeBookComponent:Lnet/minecraft/client/gui/screens/recipebook/RecipeBookComponent;
        11: aload_1
        12: aload_0
        13: invokevirtual #123                // Method isBiggerResultSlot:()Z
>       16: invokevirtual #126                // Method net/minecraft/client/gui/screens/recipebook/RecipeBookComponent.extractGhostRecipe:(Lnet/minecraft/client/gui/GuiGraphicsExtractor;Z)V
        19: return
  
    protected boolean isBiggerResultSlot();
      Code:
         0: iconst_1
         1: ireturn
  
    public boolean charTyped(net.minecraft.client.input.CharacterEvent);
>        1: getfield      #7                  // Field recipeBookComponent:Lnet/minecraft/client/gui/screens/recipebook/RecipeBookComponent;
         4: aload_1
>        5: invokevirtual #130                // Method net/minecraft/client/gui/screens/recipebook/RecipeBookComponent.charTyped:(Lnet/minecraft/client/input/CharacterEvent;)Z
         8: ifeq          13
        11: iconst_1
        12: ireturn
        13: aload_0
        14: aload_1
        15: invokespecial #134                // Method net/minecraft/client/gui/screens/inventory/AbstractContainerScreen.charTyped:(Lnet/minecraft/client/input/CharacterEvent;)Z
        18: ireturn
  
>        1: getfield      #7                  // Field recipeBookComponent:Lnet/minecraft/client/gui/screens/recipebook/RecipeBookComponent;
         4: aload_1
>        5: invokevirtual #135                // Method net/minecraft/client/gui/screens/recipebook/RecipeBookComponent.keyPressed:(Lnet/minecraft/client/input/KeyEvent;)Z
         8: ifeq          13
        11: iconst_1
        12: ireturn
        13: aload_0
        14: aload_1
        15: invokespecial #139                // Method net/minecraft/client/gui/screens/inventory/AbstractContainerScreen.keyPressed:(Lnet/minecraft/client/input/KeyEvent;)Z
        18: ireturn
  
>        1: getfield      #7                  // Field recipeBookComponent:Lnet/minecraft/client/gui/screens/recipebook/RecipeBookComponent;
         4: aload_1
         5: iload_2
>        6: invokevirtual #140                // Method net/minecraft/client/gui/screens/recipebook/RecipeBookComponent.mouseClicked:(Lnet/minecraft/client/input/MouseButtonEvent;Z)Z
         9: ifeq          22
        12: aload_0
        13: aload_0
>       14: getfield      #7                  // Field recipeBookComponent:Lnet/minecraft/client/gui/screens/recipebook/RecipeBookComponent;
        17: invokevirtual #144                // Method setFocused:(Lnet/minecraft/client/gui/components/events/GuiEventListener;)V
        20: iconst_1
        21: ireturn
        22: aload_0
        23: getfield      #21                 // Field widthTooNarrow:Z
        26: ifeq          41
        29: aload_0
>       30: getfield      #7                  // Field recipeBookComponent:Lnet/minecraft/client/gui/screens/recipebook/RecipeBookComponent;
>       33: invokevirtual #83                 // Method net/minecraft/client/gui/screens/recipebook/RecipeBookComponent.isVisible:()Z
        36: ifeq          41
        39: iconst_1
        40: ireturn
        41: aload_0
        42: aload_1
        43: iload_2
        44: invokespecial #148                // Method net/minecraft/client/gui/screens/inventory/AbstractContainerScreen.mouseClicked:(Lnet/minecraft/client/input/MouseButtonEvent;Z)Z
        47: ireturn
>        1: getfield      #7                  // Field recipeBookComponent:Lnet/minecraft/client/gui/screens/recipebook/RecipeBookComponent;
         4: aload_1
         5: dload_2
         6: dload         4
>        8: invokevirtual #149                // Method net/minecraft/client/gui/screens/recipebook/RecipeBookComponent.mouseDragged:(Lnet/minecraft/client/input/MouseButtonEvent;DD)Z
        11: ifeq          16
        14: iconst_1
        15: ireturn
        16: aload_0
        17: aload_1
        18: dload_2
        19: dload         4
        21: invokespecial #153                // Method net/minecraft/client/gui/screens/inventory/AbstractContainerScreen.mouseDragged:(Lnet/minecraft/client/input/MouseButtonEvent;DD)Z
>        8: getfield      #7                  // Field recipeBookComponent:Lnet/minecraft/client/gui/screens/recipebook/RecipeBookComponent;
>       11: invokevirtual #83                 // Method net/minecraft/client/gui/screens/recipebook/RecipeBookComponent.isVisible:()Z
        14: ifne          37
        17: aload_0
        18: iload_1
        19: iload_2
        20: iload_3
        21: iload         4
        23: dload         5
        25: dload         7
>       50: getfield      #7                  // Field recipeBookComponent:Lnet/minecraft/client/gui/screens/recipebook/RecipeBookComponent;
        53: dload_1
        54: dload_3
        55: aload_0
>       56: getfield      #44                 // Field leftPos:I
        59: aload_0
>       60: getfield      #161                // Field topPos:I
        63: aload_0
        64: getfield      #37                 // Field imageWidth:I
        67: aload_0
        68: getfield      #158                // Field imageHeight:I
>       71: invokevirtual #164                // Method net/minecraft/client/gui/screens/recipebook/RecipeBookComponent.hasClickedOutside:(DDIIII)Z
        74: ifeq          86
        77: iload         7
        79: ifeq          86
        82: iconst_1
        83: goto          87
        86: iconst_0
        87: ireturn
  
>       10: getfield      #7                  // Field recipeBookComponent:Lnet/minecraft/client/gui/screens/recipebook/RecipeBookComponent;
        13: aload_1
>       14: invokevirtual #172                // Method net/minecraft/client/gui/screens/recipebook/RecipeBookComponent.slotClicked:(Lnet/minecraft/world/inventory/Slot;)V
        17: return
  
    public void containerTick();
      Code:
         0: aload_0
         1: invokespecial #175                // Method net/minecraft/client/gui/screens/inventory/AbstractContainerScreen.containerTick:()V
         4: aload_0
>        5: getfield      #7                  // Field recipeBookComponent:Lnet/minecraft/client/gui/screens/recipebook/RecipeBookComponent;
>        8: invokevirtual #178                // Method net/minecraft/client/gui/screens/recipebook/RecipeBookComponent.tick:()V
        11: return
  
    public void recipesUpdated();
      Code:
         0: aload_0
>        1: getfield      #7                  // Field recipeBookComponent:Lnet/minecraft/client/gui/screens/recipebook/RecipeBookComponent;
>        4: invokevirtual #181                // Method net/minecraft/client/gui/screens/recipebook/RecipeBookComponent.recipesUpdated:()V
         7: return
  
    public void fillGhostRecipe(net.minecraft.world.item.crafting.display.RecipeDisplay);
      Code:
         0: aload_0
>        1: getfield      #7                  // Field recipeBookComponent:Lnet/minecraft/client/gui/screens/recipebook/RecipeBookComponent;
         4: aload_1
>        5: invokevirtual #184                // Method net/minecraft/client/gui/screens/recipebook/RecipeBookComponent.fillGhostRecipe:(Lnet/minecraft/world/item/crafting/display/RecipeDisplay;)V
         8: return
  }
