Compiled from "InventoryScreen.java"
public class net.minecraft.client.gui.screens.inventory.InventoryScreen extends net.minecraft.client.gui.screens.inventory.AbstractRecipeBookScreen<net.minecraft.world.inventory.InventoryMenu> {
  public net.minecraft.client.gui.screens.inventory.InventoryScreen(net.minecraft.world.entity.player.Player);
    Code:
       0: aload_0
       1: aload_1
       2: getfield      #1                  // Field net/minecraft/world/entity/player/Player.inventoryMenu:Lnet/minecraft/world/inventory/InventoryMenu;
       5: new           #7                  // class net/minecraft/client/gui/screens/recipebook/CraftingRecipeBookComponent
       8: dup
       9: aload_1
      10: getfield      #1                  // Field net/minecraft/world/entity/player/Player.inventoryMenu:Lnet/minecraft/world/inventory/InventoryMenu;
      13: invokespecial #9                  // Method net/minecraft/client/gui/screens/recipebook/CraftingRecipeBookComponent."<init>":(Lnet/minecraft/world/inventory/AbstractCraftingMenu;)V
      16: aload_1
      17: invokevirtual #13                 // Method net/minecraft/world/entity/player/Player.getInventory:()Lnet/minecraft/world/entity/player/Inventory;
      20: ldc           #17                 // String container.crafting
      22: invokestatic  #19                 // InterfaceMethod net/minecraft/network/chat/Component.translatable:(Ljava/lang/String;)Lnet/minecraft/network/chat/MutableComponent;
      25: invokespecial #25                 // Method net/minecraft/client/gui/screens/inventory/AbstractRecipeBookScreen."<init>":(Lnet/minecraft/world/inventory/RecipeBookMenu;Lnet/minecraft/client/gui/screens/recipebook/RecipeBookComponent;Lnet/minecraft/world/entity/player/Inventory;Lnet/minecraft/network/chat/Component;)V
      28: aload_0
      29: bipush        97
      31: putfield      #30                 // Field titleLabelX:I
      34: aload_0
      35: new           #36                 // class net/minecraft/client/gui/screens/inventory/EffectsInInventory
      38: dup
      39: aload_0
      40: invokespecial #38                 // Method net/minecraft/client/gui/screens/inventory/EffectsInInventory."<init>":(Lnet/minecraft/client/gui/screens/inventory/AbstractContainerScreen;)V
      43: putfield      #41                 // Field effects:Lnet/minecraft/client/gui/screens/inventory/EffectsInInventory;
      46: return

  public void containerTick();
    Code:
       0: aload_0
       1: invokespecial #45                 // Method net/minecraft/client/gui/screens/inventory/AbstractRecipeBookScreen.containerTick:()V
       4: aload_0
       5: getfield      #49                 // Field minecraft:Lnet/minecraft/client/Minecraft;
       8: getfield      #53                 // Field net/minecraft/client/Minecraft.player:Lnet/minecraft/client/player/LocalPlayer;
      11: invokevirtual #59                 // Method net/minecraft/client/player/LocalPlayer.hasInfiniteMaterials:()Z
      14: ifeq          70
      17: aload_0
      18: getfield      #49                 // Field minecraft:Lnet/minecraft/client/Minecraft;
      21: new           #65                 // class net/minecraft/client/gui/screens/inventory/CreativeModeInventoryScreen
      24: dup
      25: aload_0
      26: getfield      #49                 // Field minecraft:Lnet/minecraft/client/Minecraft;
      29: getfield      #53                 // Field net/minecraft/client/Minecraft.player:Lnet/minecraft/client/player/LocalPlayer;
      32: aload_0
      33: getfield      #49                 // Field minecraft:Lnet/minecraft/client/Minecraft;
      36: getfield      #53                 // Field net/minecraft/client/Minecraft.player:Lnet/minecraft/client/player/LocalPlayer;
      39: getfield      #67                 // Field net/minecraft/client/player/LocalPlayer.connection:Lnet/minecraft/client/multiplayer/ClientPacketListener;
      42: invokevirtual #71                 // Method net/minecraft/client/multiplayer/ClientPacketListener.enabledFeatures:()Lnet/minecraft/world/flag/FeatureFlagSet;
      45: aload_0
      46: getfield      #49                 // Field minecraft:Lnet/minecraft/client/Minecraft;
      49: getfield      #77                 // Field net/minecraft/client/Minecraft.options:Lnet/minecraft/client/Options;
      52: invokevirtual #81                 // Method net/minecraft/client/Options.operatorItemsTab:()Lnet/minecraft/client/OptionInstance;
      55: invokevirtual #87                 // Method net/minecraft/client/OptionInstance.get:()Ljava/lang/Object;
      58: checkcast     #93                 // class java/lang/Boolean
      61: invokevirtual #95                 // Method java/lang/Boolean.booleanValue:()Z
      64: invokespecial #98                 // Method net/minecraft/client/gui/screens/inventory/CreativeModeInventoryScreen."<init>":(Lnet/minecraft/client/player/LocalPlayer;Lnet/minecraft/world/flag/FeatureFlagSet;Z)V
      67: invokevirtual #101                // Method net/minecraft/client/Minecraft.setScreen:(Lnet/minecraft/client/gui/screens/Screen;)V
      70: return

  protected void init();
    Code:
       0: aload_0
       1: getfield      #49                 // Field minecraft:Lnet/minecraft/client/Minecraft;
       4: getfield      #53                 // Field net/minecraft/client/Minecraft.player:Lnet/minecraft/client/player/LocalPlayer;
       7: invokevirtual #59                 // Method net/minecraft/client/player/LocalPlayer.hasInfiniteMaterials:()Z
      10: ifeq          67
      13: aload_0
      14: getfield      #49                 // Field minecraft:Lnet/minecraft/client/Minecraft;
      17: new           #65                 // class net/minecraft/client/gui/screens/inventory/CreativeModeInventoryScreen
      20: dup
      21: aload_0
      22: getfield      #49                 // Field minecraft:Lnet/minecraft/client/Minecraft;
      25: getfield      #53                 // Field net/minecraft/client/Minecraft.player:Lnet/minecraft/client/player/LocalPlayer;
      28: aload_0
      29: getfield      #49                 // Field minecraft:Lnet/minecraft/client/Minecraft;
      32: getfield      #53                 // Field net/minecraft/client/Minecraft.player:Lnet/minecraft/client/player/LocalPlayer;
      35: getfield      #67                 // Field net/minecraft/client/player/LocalPlayer.connection:Lnet/minecraft/client/multiplayer/ClientPacketListener;
      38: invokevirtual #71                 // Method net/minecraft/client/multiplayer/ClientPacketListener.enabledFeatures:()Lnet/minecraft/world/flag/FeatureFlagSet;
      41: aload_0
      42: getfield      #49                 // Field minecraft:Lnet/minecraft/client/Minecraft;
      45: getfield      #77                 // Field net/minecraft/client/Minecraft.options:Lnet/minecraft/client/Options;
      48: invokevirtual #81                 // Method net/minecraft/client/Options.operatorItemsTab:()Lnet/minecraft/client/OptionInstance;
      51: invokevirtual #87                 // Method net/minecraft/client/OptionInstance.get:()Ljava/lang/Object;
      54: checkcast     #93                 // class java/lang/Boolean
      57: invokevirtual #95                 // Method java/lang/Boolean.booleanValue:()Z
      60: invokespecial #98                 // Method net/minecraft/client/gui/screens/inventory/CreativeModeInventoryScreen."<init>":(Lnet/minecraft/client/player/LocalPlayer;Lnet/minecraft/world/flag/FeatureFlagSet;Z)V
      63: invokevirtual #101                // Method net/minecraft/client/Minecraft.setScreen:(Lnet/minecraft/client/gui/screens/Screen;)V
      66: return
      67: aload_0
      68: invokespecial #105                // Method net/minecraft/client/gui/screens/inventory/AbstractRecipeBookScreen.init:()V
      71: return

  protected net.minecraft.client.gui.navigation.ScreenPosition getRecipeBookButtonPosition();
    Code:
       0: new           #108                // class net/minecraft/client/gui/navigation/ScreenPosition
       3: dup
       4: aload_0
       5: getfield      #110                // Field leftPos:I
       8: bipush        104
      10: iadd
      11: aload_0
      12: getfield      #113                // Field height:I
      15: iconst_2
      16: idiv
      17: bipush        22
      19: isub
      20: invokespecial #116                // Method net/minecraft/client/gui/navigation/ScreenPosition."<init>":(II)V
      23: areturn

  protected void onRecipeBookButtonClick();
    Code:
       0: aload_0
       1: iconst_1
       2: putfield      #119                // Field buttonClicked:Z
       5: return

  protected void extractLabels(net.minecraft.client.gui.GuiGraphicsExtractor, int, int);
    Code:
       0: aload_1
       1: aload_0
       2: getfield      #123                // Field font:Lnet/minecraft/client/gui/Font;
       5: aload_0
       6: getfield      #127                // Field title:Lnet/minecraft/network/chat/Component;
       9: aload_0
      10: getfield      #30                 // Field titleLabelX:I
      13: aload_0
      14: getfield      #131                // Field titleLabelY:I
      17: ldc           #136                // int -12566464
      19: iconst_0
      20: invokevirtual #137                // Method net/minecraft/client/gui/GuiGraphicsExtractor.text:(Lnet/minecraft/client/gui/Font;Lnet/minecraft/network/chat/Component;IIIZ)V
      23: return

  public void extractRenderState(net.minecraft.client.gui.GuiGraphicsExtractor, int, int, float);
    Code:
       0: aload_0
       1: getfield      #41                 // Field effects:Lnet/minecraft/client/gui/screens/inventory/EffectsInInventory;
       4: aload_1
       5: iload_2
       6: iload_3
       7: invokevirtual #143                // Method net/minecraft/client/gui/screens/inventory/EffectsInInventory.extractRenderState:(Lnet/minecraft/client/gui/GuiGraphicsExtractor;II)V
      10: aload_0
      11: aload_1
      12: iload_2
      13: iload_3
      14: fload         4
      16: invokespecial #147                // Method net/minecraft/client/gui/screens/inventory/AbstractRecipeBookScreen.extractRenderState:(Lnet/minecraft/client/gui/GuiGraphicsExtractor;IIF)V
      19: aload_0
      20: iload_2
      21: i2f
      22: putfield      #150                // Field xMouse:F
      25: aload_0
      26: iload_3
      27: i2f
      28: putfield      #154                // Field yMouse:F
      31: return

  public boolean showsActiveEffects();
    Code:
       0: aload_0
       1: getfield      #41                 // Field effects:Lnet/minecraft/client/gui/screens/inventory/EffectsInInventory;
       4: invokevirtual #157                // Method net/minecraft/client/gui/screens/inventory/EffectsInInventory.canSeeEffects:()Z
       7: ireturn

  protected boolean isBiggerResultSlot();
    Code:
       0: iconst_0
       1: ireturn

  public void extractBackground(net.minecraft.client.gui.GuiGraphicsExtractor, int, int, float);
    Code:
       0: aload_0
       1: aload_1
       2: iload_2
       3: iload_3
       4: fload         4
       6: invokespecial #160                // Method net/minecraft/client/gui/screens/inventory/AbstractRecipeBookScreen.extractBackground:(Lnet/minecraft/client/gui/GuiGraphicsExtractor;IIF)V
       9: aload_0
      10: getfield      #110                // Field leftPos:I
      13: istore        5
      15: aload_0
      16: getfield      #163                // Field topPos:I
      19: istore        6
      21: aload_1
      22: getstatic     #166                // Field net/minecraft/client/renderer/RenderPipelines.GUI_TEXTURED:Lcom/mojang/blaze3d/pipeline/RenderPipeline;
      25: getstatic     #172                // Field INVENTORY_LOCATION:Lnet/minecraft/resources/Identifier;
      28: iload         5
      30: iload         6
      32: fconst_0
      33: fconst_0
      34: aload_0
      35: getfield      #176                // Field imageWidth:I
      38: aload_0
      39: getfield      #179                // Field imageHeight:I
      42: sipush        256
      45: sipush        256
      48: invokevirtual #184                // Method net/minecraft/client/gui/GuiGraphicsExtractor.blit:(Lcom/mojang/blaze3d/pipeline/RenderPipeline;Lnet/minecraft/resources/Identifier;IIFFIIII)V
      51: aload_1
      52: iload         5
      54: bipush        26
      56: iadd
      57: iload         6
      59: bipush        8
      61: iadd
      62: iload         5
      64: bipush        75
      66: iadd
      67: iload         6
      69: bipush        78
      71: iadd
      72: bipush        30
      74: ldc           #188                // float 0.0625f
      76: aload_0
      77: getfield      #150                // Field xMouse:F
      80: aload_0
      81: getfield      #154                // Field yMouse:F
      84: aload_0
      85: getfield      #49                 // Field minecraft:Lnet/minecraft/client/Minecraft;
      88: getfield      #53                 // Field net/minecraft/client/Minecraft.player:Lnet/minecraft/client/player/LocalPlayer;
      91: invokestatic  #189                // Method extractEntityInInventoryFollowsMouse:(Lnet/minecraft/client/gui/GuiGraphicsExtractor;IIIIIFFFLnet/minecraft/world/entity/LivingEntity;)V
      94: return

  public static void extractEntityInInventoryFollowsMouse(net.minecraft.client.gui.GuiGraphicsExtractor, int, int, int, int, int, float, float, float, net.minecraft.world.entity.LivingEntity);
    Code:
       0: iload_1
       1: iload_3
       2: iadd
       3: i2f
       4: fconst_2
       5: fdiv
       6: fstore        10
       8: iload_2
       9: iload         4
      11: iadd
      12: i2f
      13: fconst_2
      14: fdiv
      15: fstore        11
      17: fload         10
      19: fload         7
      21: fsub
      22: ldc           #193                // float 40.0f
      24: fdiv
      25: f2d
      26: invokestatic  #194                // Method java/lang/Math.atan:(D)D
      29: d2f
      30: fstore        12
      32: fload         11
      34: fload         8
      36: fsub
      37: ldc           #193                // float 40.0f
      39: fdiv
      40: f2d
      41: invokestatic  #194                // Method java/lang/Math.atan:(D)D
      44: d2f
      45: fstore        13
      47: new           #200                // class org/joml/Quaternionf
      50: dup
      51: invokespecial #202                // Method org/joml/Quaternionf."<init>":()V
      54: ldc           #206                // float 3.1415927f
      56: invokevirtual #207                // Method org/joml/Quaternionf.rotateZ:(F)Lorg/joml/Quaternionf;
      59: astore        14
      61: new           #200                // class org/joml/Quaternionf
      64: dup
      65: invokespecial #202                // Method org/joml/Quaternionf."<init>":()V
      68: fload         13
      70: ldc           #211                // float 20.0f
      72: fmul
      73: ldc           #212                // float 0.017453292f
      75: fmul
      76: invokevirtual #213                // Method org/joml/Quaternionf.rotateX:(F)Lorg/joml/Quaternionf;
      79: astore        15
      81: aload         14
      83: aload         15
      85: invokevirtual #216                // Method org/joml/Quaternionf.mul:(Lorg/joml/Quaternionfc;)Lorg/joml/Quaternionf;
      88: pop
      89: aload         9
      91: invokestatic  #220                // Method extractRenderState:(Lnet/minecraft/world/entity/LivingEntity;)Lnet/minecraft/client/renderer/entity/state/EntityRenderState;
      94: astore        16
      96: aload         16
      98: instanceof    #223                // class net/minecraft/client/renderer/entity/state/LivingEntityRenderState
     101: ifeq          201
     104: aload         16
     106: checkcast     #223                // class net/minecraft/client/renderer/entity/state/LivingEntityRenderState
     109: astore        17
     111: aload         17
     113: ldc           #225                // float 180.0f
     115: fload         12
     117: ldc           #211                // float 20.0f
     119: fmul
     120: fadd
     121: putfield      #226                // Field net/minecraft/client/renderer/entity/state/LivingEntityRenderState.bodyRot:F
     124: aload         17
     126: fload         12
     128: ldc           #211                // float 20.0f
     130: fmul
     131: putfield      #229                // Field net/minecraft/client/renderer/entity/state/LivingEntityRenderState.yRot:F
     134: aload         17
     136: getfield      #232                // Field net/minecraft/client/renderer/entity/state/LivingEntityRenderState.pose:Lnet/minecraft/world/entity/Pose;
     139: getstatic     #236                // Field net/minecraft/world/entity/Pose.FALL_FLYING:Lnet/minecraft/world/entity/Pose;
     142: if_acmpeq     159
     145: aload         17
     147: fload         13
     149: fneg
     150: ldc           #211                // float 20.0f
     152: fmul
     153: putfield      #241                // Field net/minecraft/client/renderer/entity/state/LivingEntityRenderState.xRot:F
     156: goto          165
     159: aload         17
     161: fconst_0
     162: putfield      #241                // Field net/minecraft/client/renderer/entity/state/LivingEntityRenderState.xRot:F
     165: aload         17
     167: dup
     168: getfield      #244                // Field net/minecraft/client/renderer/entity/state/LivingEntityRenderState.boundingBoxWidth:F
     171: aload         17
     173: getfield      #247                // Field net/minecraft/client/renderer/entity/state/LivingEntityRenderState.scale:F
     176: fdiv
     177: putfield      #244                // Field net/minecraft/client/renderer/entity/state/LivingEntityRenderState.boundingBoxWidth:F
     180: aload         17
     182: dup
     183: getfield      #250                // Field net/minecraft/client/renderer/entity/state/LivingEntityRenderState.boundingBoxHeight:F
     186: aload         17
     188: getfield      #247                // Field net/minecraft/client/renderer/entity/state/LivingEntityRenderState.scale:F
     191: fdiv
     192: putfield      #250                // Field net/minecraft/client/renderer/entity/state/LivingEntityRenderState.boundingBoxHeight:F
     195: aload         17
     197: fconst_1
     198: putfield      #247                // Field net/minecraft/client/renderer/entity/state/LivingEntityRenderState.scale:F
     201: new           #253                // class org/joml/Vector3f
     204: dup
     205: fconst_0
     206: aload         16
     208: getfield      #255                // Field net/minecraft/client/renderer/entity/state/EntityRenderState.boundingBoxHeight:F
     211: fconst_2
     212: fdiv
     213: fload         6
     215: fadd
     216: fconst_0
     217: invokespecial #258                // Method org/joml/Vector3f."<init>":(FFF)V
     220: astore        17
     222: aload_0
     223: aload         16
     225: iload         5
     227: i2f
     228: aload         17
     230: aload         14
     232: aload         15
     234: iload_1
     235: iload_2
     236: iload_3
     237: iload         4
     239: invokevirtual #261                // Method net/minecraft/client/gui/GuiGraphicsExtractor.entity:(Lnet/minecraft/client/renderer/entity/state/EntityRenderState;FLorg/joml/Vector3f;Lorg/joml/Quaternionf;Lorg/joml/Quaternionf;IIII)V
     242: return

  public boolean mouseReleased(net.minecraft.client.input.MouseButtonEvent);
    Code:
       0: aload_0
       1: getfield      #119                // Field buttonClicked:Z
       4: ifeq          14
       7: aload_0
       8: iconst_0
       9: putfield      #119                // Field buttonClicked:Z
      12: iconst_1
      13: ireturn
      14: aload_0
      15: aload_1
      16: invokespecial #297                // Method net/minecraft/client/gui/screens/inventory/AbstractRecipeBookScreen.mouseReleased:(Lnet/minecraft/client/input/MouseButtonEvent;)Z
      19: ireturn
}
