Compiled from "RecipeBookComponent.java"
public abstract class net.minecraft.client.gui.screens.recipebook.RecipeBookComponent<T extends net.minecraft.world.inventory.RecipeBookMenu> implements net.minecraft.client.gui.components.events.GuiEventListener, net.minecraft.client.gui.components.Renderable, net.minecraft.client.gui.narration.NarratableEntry {
  public static final net.minecraft.client.gui.components.WidgetSprites RECIPE_BUTTON_SPRITES;

  protected static final net.minecraft.resources.Identifier RECIPE_BOOK_LOCATION;

  public static final int IMAGE_WIDTH;

  public static final int IMAGE_HEIGHT;

  protected net.minecraft.client.gui.components.CycleButton<java.lang.Boolean> filterButton;

  protected final T menu;

  protected net.minecraft.client.Minecraft minecraft;

  public net.minecraft.client.gui.screens.recipebook.RecipeBookComponent(T, java.util.List<net.minecraft.client.gui.screens.recipebook.RecipeBookComponent$TabInfo>);
    Code:
       0: aload_0
       1: invokespecial #1                  // Method java/lang/Object."<init>":()V
       4: aload_0
       5: invokestatic  #7                  // Method com/google/common/collect/Lists.newArrayList:()Ljava/util/ArrayList;
       8: putfield      #13                 // Field tabButtons:Ljava/util/List;
      11: aload_0
      12: ldc           #19                 // String
      14: putfield      #21                 // Field lastSearch:Ljava/lang/String;
      17: aload_0
      18: new           #25                 // class net/minecraft/world/entity/player/StackedItemContents
      21: dup
      22: invokespecial #27                 // Method net/minecraft/world/entity/player/StackedItemContents."<init>":()V
      25: putfield      #28                 // Field stackedContents:Lnet/minecraft/world/entity/player/StackedItemContents;
      28: aload_0
      29: aload_1
      30: putfield      #32                 // Field menu:Lnet/minecraft/world/inventory/RecipeBookMenu;
      33: aload_0
      34: aload_2
      35: putfield      #36                 // Field tabInfos:Ljava/util/List;
      38: aload_0
      39: invokedynamic #39,  0             // InvokeDynamic #0:currentIndex:(Lnet/minecraft/client/gui/screens/recipebook/RecipeBookComponent;)Lnet/minecraft/client/gui/screens/recipebook/SlotSelectTime;
      44: astore_3
      45: aload_0
      46: new           #43                 // class net/minecraft/client/gui/screens/recipebook/GhostSlots
      49: dup
      50: aload_3
      51: invokespecial #45                 // Method net/minecraft/client/gui/screens/recipebook/GhostSlots."<init>":(Lnet/minecraft/client/gui/screens/recipebook/SlotSelectTime;)V
      54: putfield      #48                 // Field ghostSlots:Lnet/minecraft/client/gui/screens/recipebook/GhostSlots;
      57: aload_0
      58: new           #52                 // class net/minecraft/client/gui/screens/recipebook/RecipeBookPage
      61: dup
      62: aload_0
      63: aload_3
      64: aload_1
      65: instanceof    #54                 // class net/minecraft/world/inventory/AbstractFurnaceMenu
      68: invokespecial #56                 // Method net/minecraft/client/gui/screens/recipebook/RecipeBookPage."<init>":(Lnet/minecraft/client/gui/screens/recipebook/RecipeBookComponent;Lnet/minecraft/client/gui/screens/recipebook/SlotSelectTime;Z)V
      71: putfield      #59                 // Field recipeBookPage:Lnet/minecraft/client/gui/screens/recipebook/RecipeBookPage;
      74: return

  public void init(int, int, net.minecraft.client.Minecraft, boolean);
    Code:
       0: aload_0
       1: aload_3
       2: putfield      #63                 // Field minecraft:Lnet/minecraft/client/Minecraft;
       5: aload_0
       6: iload_1
       7: putfield      #67                 // Field width:I
      10: aload_0
      11: iload_2
      12: putfield      #71                 // Field height:I
      15: aload_0
      16: iload         4
      18: putfield      #74                 // Field widthTooNarrow:Z
      21: aload_0
      22: aload_3
      23: getfield      #78                 // Field net/minecraft/client/Minecraft.player:Lnet/minecraft/client/player/LocalPlayer;
      26: invokevirtual #84                 // Method net/minecraft/client/player/LocalPlayer.getRecipeBook:()Lnet/minecraft/client/ClientRecipeBook;
      29: putfield      #90                 // Field book:Lnet/minecraft/client/ClientRecipeBook;
      32: aload_0
      33: aload_3
      34: getfield      #78                 // Field net/minecraft/client/Minecraft.player:Lnet/minecraft/client/player/LocalPlayer;
      37: invokevirtual #94                 // Method net/minecraft/client/player/LocalPlayer.getInventory:()Lnet/minecraft/world/entity/player/Inventory;
      40: invokevirtual #98                 // Method net/minecraft/world/entity/player/Inventory.getTimesChanged:()I
      43: putfield      #104                // Field timesInventoryChanged:I
      46: aload_0
      47: aload_0
      48: invokevirtual #107                // Method isVisibleAccordingToBookData:()Z
      51: putfield      #111                // Field visible:Z
      54: aload_0
      55: getfield      #111                // Field visible:Z
      58: ifeq          65
      61: aload_0
      62: invokevirtual #114                // Method initVisuals:()V
      65: return

  protected abstract net.minecraft.client.gui.components.WidgetSprites getFilterButtonTextures();

  public int updateScreenPosition(int, int);
    Code:
       0: aload_0
       1: invokevirtual #358                // Method isVisible:()Z
       4: ifeq          31
       7: aload_0
       8: getfield      #74                 // Field widthTooNarrow:Z
      11: ifne          31
      14: sipush        177
      17: iload_1
      18: iload_2
      19: isub
      20: sipush        200
      23: isub
      24: iconst_2
      25: idiv
      26: iadd
      27: istore_3
      28: goto          37
      31: iload_1
      32: iload_2
      33: isub
      34: iconst_2
      35: idiv
      36: istore_3
      37: iload_3
      38: ireturn

  public void toggleVisibility();
    Code:
       0: aload_0
       1: aload_0
       2: invokevirtual #358                // Method isVisible:()Z
       5: ifne          12
       8: iconst_1
       9: goto          13
      12: iconst_0
      13: invokevirtual #361                // Method setVisible:(Z)V
      16: return

  public boolean isVisible();
    Code:
       0: aload_0
       1: getfield      #111                // Field visible:Z
       4: ireturn

  protected void setVisible(boolean);
    Code:
       0: iload_1
       1: ifeq          8
       4: aload_0
       5: invokevirtual #114                // Method initVisuals:()V
       8: aload_0
       9: iload_1
      10: putfield      #111                // Field visible:Z
      13: aload_0
      14: getfield      #90                 // Field book:Lnet/minecraft/client/ClientRecipeBook;
      17: aload_0
      18: getfield      #32                 // Field menu:Lnet/minecraft/world/inventory/RecipeBookMenu;
      21: invokevirtual #362                // Method net/minecraft/world/inventory/RecipeBookMenu.getRecipeBookType:()Lnet/minecraft/world/inventory/RecipeBookType;
      24: iload_1
      25: invokevirtual #372                // Method net/minecraft/client/ClientRecipeBook.setOpen:(Lnet/minecraft/world/inventory/RecipeBookType;Z)V
      28: iload_1
      29: ifne          39
      32: aload_0
      33: getfield      #59                 // Field recipeBookPage:Lnet/minecraft/client/gui/screens/recipebook/RecipeBookPage;
      36: invokevirtual #376                // Method net/minecraft/client/gui/screens/recipebook/RecipeBookPage.setInvisible:()V
      39: aload_0
      40: invokevirtual #379                // Method sendUpdateSettings:()V
      43: return

  protected abstract boolean isCraftingSlot(net.minecraft.world.inventory.Slot);

  public void slotClicked(net.minecraft.world.inventory.Slot);
    Code:
       0: aload_1
       1: ifnull        35
       4: aload_0
       5: aload_1
       6: invokevirtual #382                // Method isCraftingSlot:(Lnet/minecraft/world/inventory/Slot;)Z
       9: ifeq          35
      12: aload_0
      13: aconst_null
      14: putfield      #386                // Field lastPlacedRecipe:Lnet/minecraft/world/item/crafting/display/RecipeDisplayId;
      17: aload_0
      18: getfield      #48                 // Field ghostSlots:Lnet/minecraft/client/gui/screens/recipebook/GhostSlots;
      21: invokevirtual #390                // Method net/minecraft/client/gui/screens/recipebook/GhostSlots.clear:()V
      24: aload_0
      25: invokevirtual #358                // Method isVisible:()Z
      28: ifeq          35
      31: aload_0
      32: invokevirtual #391                // Method updateStackedContents:()V
      35: return

  protected abstract void selectMatchingRecipes(net.minecraft.client.gui.screens.recipebook.RecipeCollection, net.minecraft.world.entity.player.StackedItemContents);

  public void tick();
    Code:
       0: aload_0
       1: invokevirtual #107                // Method isVisibleAccordingToBookData:()Z
       4: istore_1
       5: aload_0
       6: invokevirtual #358                // Method isVisible:()Z
       9: iload_1
      10: if_icmpeq     18
      13: aload_0
      14: iload_1
      15: invokevirtual #361                // Method setVisible:(Z)V
      18: aload_0
      19: invokevirtual #358                // Method isVisible:()Z
      22: ifne          26
      25: return
      26: aload_0
      27: getfield      #104                // Field timesInventoryChanged:I
      30: aload_0
      31: getfield      #63                 // Field minecraft:Lnet/minecraft/client/Minecraft;
      34: getfield      #78                 // Field net/minecraft/client/Minecraft.player:Lnet/minecraft/client/player/LocalPlayer;
      37: invokevirtual #94                 // Method net/minecraft/client/player/LocalPlayer.getInventory:()Lnet/minecraft/world/entity/player/Inventory;
      40: invokevirtual #98                 // Method net/minecraft/world/entity/player/Inventory.getTimesChanged:()I
      43: if_icmpeq     67
      46: aload_0
      47: invokevirtual #391                // Method updateStackedContents:()V
      50: aload_0
      51: aload_0
      52: getfield      #63                 // Field minecraft:Lnet/minecraft/client/Minecraft;
      55: getfield      #78                 // Field net/minecraft/client/Minecraft.player:Lnet/minecraft/client/player/LocalPlayer;
      58: invokevirtual #94                 // Method net/minecraft/client/player/LocalPlayer.getInventory:()Lnet/minecraft/world/entity/player/Inventory;
      61: invokevirtual #98                 // Method net/minecraft/world/entity/player/Inventory.getTimesChanged:()I
      64: putfield      #104                // Field timesInventoryChanged:I
      67: return

  public void extractRenderState(net.minecraft.client.gui.GuiGraphicsExtractor, int, int, float);
    Code:
       0: aload_0
       1: invokevirtual #358                // Method isVisible:()Z
       4: ifne          8
       7: return
       8: aload_0
       9: getfield      #63                 // Field minecraft:Lnet/minecraft/client/Minecraft;
      12: invokevirtual #486                // Method net/minecraft/client/Minecraft.hasControlDown:()Z
      15: ifne          29
      18: aload_0
      19: dup
      20: getfield      #489                // Field time:F
      23: fload         4
      25: fadd
      26: putfield      #489                // Field time:F
      29: aload_0
      30: invokevirtual #123                // Method getXOrigin:()I
      33: istore        5
      35: aload_0
      36: invokevirtual #126                // Method getYOrigin:()I
      39: istore        6
      41: aload_1
      42: getstatic     #493                // Field net/minecraft/client/renderer/RenderPipelines.GUI_TEXTURED:Lcom/mojang/blaze3d/pipeline/RenderPipeline;
      45: getstatic     #499                // Field RECIPE_BOOK_LOCATION:Lnet/minecraft/resources/Identifier;
      48: iload         5
      50: iload         6
      52: fconst_1
      53: fconst_1
      54: sipush        147
      57: sipush        166
      60: sipush        256
      63: sipush        256
      66: invokevirtual #503                // Method net/minecraft/client/gui/GuiGraphicsExtractor.blit:(Lcom/mojang/blaze3d/pipeline/RenderPipeline;Lnet/minecraft/resources/Identifier;IIFFIIII)V
      69: aload_0
      70: getfield      #141                // Field searchBox:Lnet/minecraft/client/gui/components/EditBox;
      73: aload_1
      74: iload_2
      75: iload_3
      76: fload         4
      78: invokevirtual #509                // Method net/minecraft/client/gui/components/EditBox.extractRenderState:(Lnet/minecraft/client/gui/GuiGraphicsExtractor;IIF)V
      81: aload_0
      82: getfield      #13                 // Field tabButtons:Ljava/util/List;
      85: invokeinterface #286,  1          // InterfaceMethod java/util/List.iterator:()Ljava/util/Iterator;
      90: astore        7
      92: aload         7
      94: invokeinterface #290,  1          // InterfaceMethod java/util/Iterator.hasNext:()Z
      99: ifeq          127
     102: aload         7
     104: invokeinterface #295,  1          // InterfaceMethod java/util/Iterator.next:()Ljava/lang/Object;
     109: checkcast     #301                // class net/minecraft/client/gui/screens/recipebook/RecipeBookTabButton
     112: astore        8
     114: aload         8
     116: aload_1
     117: iload_2
     118: iload_3
     119: fload         4
     121: invokevirtual #513                // Method net/minecraft/client/gui/screens/recipebook/RecipeBookTabButton.extractRenderState:(Lnet/minecraft/client/gui/GuiGraphicsExtractor;IIF)V
     124: goto          92
     127: aload_0
     128: getfield      #279                // Field filterButton:Lnet/minecraft/client/gui/components/CycleButton;
     131: aload_1
     132: iload_2
     133: iload_3
     134: fload         4
     136: invokevirtual #514                // Method net/minecraft/client/gui/components/CycleButton.extractRenderState:(Lnet/minecraft/client/gui/GuiGraphicsExtractor;IIF)V
     139: aload_0
     140: getfield      #59                 // Field recipeBookPage:Lnet/minecraft/client/gui/screens/recipebook/RecipeBookPage;
     143: aload_1
     144: iload         5
     146: iload         6
     148: iload_2
     149: iload_3
     150: fload         4
     152: invokevirtual #515                // Method net/minecraft/client/gui/screens/recipebook/RecipeBookPage.extractRenderState:(Lnet/minecraft/client/gui/GuiGraphicsExtractor;IIIIF)V
     155: return

  public void extractTooltip(net.minecraft.client.gui.GuiGraphicsExtractor, int, int, net.minecraft.world.inventory.Slot);
    Code:
       0: aload_0
       1: invokevirtual #358                // Method isVisible:()Z
       4: ifne          8
       7: return
       8: aload_0
       9: getfield      #59                 // Field recipeBookPage:Lnet/minecraft/client/gui/screens/recipebook/RecipeBookPage;
      12: aload_1
      13: iload_2
      14: iload_3
      15: invokevirtual #518                // Method net/minecraft/client/gui/screens/recipebook/RecipeBookPage.extractTooltip:(Lnet/minecraft/client/gui/GuiGraphicsExtractor;II)V
      18: aload_0
      19: getfield      #48                 // Field ghostSlots:Lnet/minecraft/client/gui/screens/recipebook/GhostSlots;
      22: aload_1
      23: aload_0
      24: getfield      #63                 // Field minecraft:Lnet/minecraft/client/Minecraft;
      27: iload_2
      28: iload_3
      29: aload         4
      31: invokevirtual #522                // Method net/minecraft/client/gui/screens/recipebook/GhostSlots.extractTooltip:(Lnet/minecraft/client/gui/GuiGraphicsExtractor;Lnet/minecraft/client/Minecraft;IILnet/minecraft/world/inventory/Slot;)V
      34: return

  protected abstract net.minecraft.network.chat.Component getRecipeFilterName();

  public void extractGhostRecipe(net.minecraft.client.gui.GuiGraphicsExtractor, boolean);
    Code:
       0: aload_0
       1: getfield      #48                 // Field ghostSlots:Lnet/minecraft/client/gui/screens/recipebook/GhostSlots;
       4: aload_1
       5: aload_0
       6: getfield      #63                 // Field minecraft:Lnet/minecraft/client/Minecraft;
       9: iload_2
      10: invokevirtual #525                // Method net/minecraft/client/gui/screens/recipebook/GhostSlots.extractRenderState:(Lnet/minecraft/client/gui/GuiGraphicsExtractor;Lnet/minecraft/client/Minecraft;Z)V
      13: return

  public boolean mouseClicked(net.minecraft.client.input.MouseButtonEvent, boolean);
    Code:
       0: aload_0
       1: invokevirtual #358                // Method isVisible:()Z
       4: ifeq          20
       7: aload_0
       8: getfield      #63                 // Field minecraft:Lnet/minecraft/client/Minecraft;
      11: getfield      #78                 // Field net/minecraft/client/Minecraft.player:Lnet/minecraft/client/player/LocalPlayer;
      14: invokevirtual #528                // Method net/minecraft/client/player/LocalPlayer.isSpectator:()Z
      17: ifeq          22
      20: iconst_0
      21: ireturn
      22: aload_0
      23: getfield      #59                 // Field recipeBookPage:Lnet/minecraft/client/gui/screens/recipebook/RecipeBookPage;
      26: aload_1
      27: aload_0
      28: invokevirtual #123                // Method getXOrigin:()I
      31: aload_0
      32: invokevirtual #126                // Method getYOrigin:()I
      35: sipush        147
      38: sipush        166
      41: iload_2
      42: invokevirtual #531                // Method net/minecraft/client/gui/screens/recipebook/RecipeBookPage.mouseClicked:(Lnet/minecraft/client/input/MouseButtonEvent;IIIIZ)Z
      45: ifeq          115
      48: aload_0
      49: getfield      #59                 // Field recipeBookPage:Lnet/minecraft/client/gui/screens/recipebook/RecipeBookPage;
      52: invokevirtual #535                // Method net/minecraft/client/gui/screens/recipebook/RecipeBookPage.getLastClickedRecipe:()Lnet/minecraft/world/item/crafting/display/RecipeDisplayId;
      55: astore_3
      56: aload_0
      57: getfield      #59                 // Field recipeBookPage:Lnet/minecraft/client/gui/screens/recipebook/RecipeBookPage;
      60: invokevirtual #539                // Method net/minecraft/client/gui/screens/recipebook/RecipeBookPage.getLastClickedRecipeCollection:()Lnet/minecraft/client/gui/screens/recipebook/RecipeCollection;
      63: astore        4
      65: aload_3
      66: ifnull        113
      69: aload         4
      71: ifnull        113
      74: aload_0
      75: aload         4
      77: aload_3
      78: aload_1
      79: invokevirtual #543                // Method net/minecraft/client/input/MouseButtonEvent.hasShiftDown:()Z
      82: invokevirtual #548                // Method tryPlaceRecipe:(Lnet/minecraft/client/gui/screens/recipebook/RecipeCollection;Lnet/minecraft/world/item/crafting/display/RecipeDisplayId;Z)Z
      85: ifne          90
      88: iconst_0
      89: ireturn
      90: aload_0
      91: aload         4
      93: putfield      #552                // Field lastRecipeCollection:Lnet/minecraft/client/gui/screens/recipebook/RecipeCollection;
      96: aload_0
      97: aload_3
      98: putfield      #556                // Field lastRecipe:Lnet/minecraft/world/item/crafting/display/RecipeDisplayId;
     101: aload_0
     102: invokevirtual #559                // Method isOffsetNextToMainGUI:()Z
     105: ifne          113
     108: aload_0
     109: iconst_0
     110: invokevirtual #361                // Method setVisible:(Z)V
     113: iconst_1
     114: ireturn
     115: aload_0
     116: getfield      #141                // Field searchBox:Lnet/minecraft/client/gui/components/EditBox;
     119: ifnull        193
     122: aload_0
     123: getfield      #218                // Field magnifierIconPlacement:Lnet/minecraft/client/gui/navigation/ScreenRectangle;
     126: ifnull        157
     129: aload_0
     130: getfield      #218                // Field magnifierIconPlacement:Lnet/minecraft/client/gui/navigation/ScreenRectangle;
     133: aload_1
     134: invokevirtual #562                // Method net/minecraft/client/input/MouseButtonEvent.x:()D
     137: invokestatic  #566                // Method net/minecraft/util/Mth.floor:(D)I
     140: aload_1
     141: invokevirtual #572                // Method net/minecraft/client/input/MouseButtonEvent.y:()D
     144: invokestatic  #566                // Method net/minecraft/util/Mth.floor:(D)I
     147: invokevirtual #575                // Method net/minecraft/client/gui/navigation/ScreenRectangle.containsPoint:(II)Z
     150: ifeq          157
     153: iconst_1
     154: goto          158
     157: iconst_0
     158: istore_3
     159: iload_3
     160: ifne          175
     163: aload_0
     164: getfield      #141                // Field searchBox:Lnet/minecraft/client/gui/components/EditBox;
     167: aload_1
     168: iload_2
     169: invokevirtual #579                // Method net/minecraft/client/gui/components/EditBox.mouseClicked:(Lnet/minecraft/client/input/MouseButtonEvent;Z)Z
     172: ifeq          185
     175: aload_0
     176: getfield      #141                // Field searchBox:Lnet/minecraft/client/gui/components/EditBox;
     179: iconst_1
     180: invokevirtual #582                // Method net/minecraft/client/gui/components/EditBox.setFocused:(Z)V
     183: iconst_1
     184: ireturn
     185: aload_0
     186: getfield      #141                // Field searchBox:Lnet/minecraft/client/gui/components/EditBox;
     189: iconst_0
     190: invokevirtual #582                // Method net/minecraft/client/gui/components/EditBox.setFocused:(Z)V
     193: aload_0
     194: getfield      #279                // Field filterButton:Lnet/minecraft/client/gui/components/CycleButton;
     197: aload_1
     198: iload_2
     199: invokevirtual #585                // Method net/minecraft/client/gui/components/CycleButton.mouseClicked:(Lnet/minecraft/client/input/MouseButtonEvent;Z)Z
     202: ifeq          207
     205: iconst_1
     206: ireturn
     207: aload_0
     208: getfield      #13                 // Field tabButtons:Ljava/util/List;
     211: invokeinterface #286,  1          // InterfaceMethod java/util/List.iterator:()Ljava/util/Iterator;
     216: astore_3
     217: aload_3
     218: invokeinterface #290,  1          // InterfaceMethod java/util/Iterator.hasNext:()Z
     223: ifeq          252
     226: aload_3
     227: invokeinterface #295,  1          // InterfaceMethod java/util/Iterator.next:()Ljava/lang/Object;
     232: checkcast     #301                // class net/minecraft/client/gui/screens/recipebook/RecipeBookTabButton
     235: astore        4
     237: aload         4
     239: aload_1
     240: iload_2
     241: invokevirtual #586                // Method net/minecraft/client/gui/screens/recipebook/RecipeBookTabButton.mouseClicked:(Lnet/minecraft/client/input/MouseButtonEvent;Z)Z
     244: ifeq          249
     247: iconst_1
     248: ireturn
     249: goto          217
     252: iconst_0
     253: ireturn

  public boolean mouseDragged(net.minecraft.client.input.MouseButtonEvent, double, double);
    Code:
       0: aload_0
       1: getfield      #141                // Field searchBox:Lnet/minecraft/client/gui/components/EditBox;
       4: ifnull        29
       7: aload_0
       8: getfield      #141                // Field searchBox:Lnet/minecraft/client/gui/components/EditBox;
      11: invokevirtual #587                // Method net/minecraft/client/gui/components/EditBox.isFocused:()Z
      14: ifeq          29
      17: aload_0
      18: getfield      #141                // Field searchBox:Lnet/minecraft/client/gui/components/EditBox;
      21: aload_1
      22: dload_2
      23: dload         4
      25: invokevirtual #590                // Method net/minecraft/client/gui/components/EditBox.mouseDragged:(Lnet/minecraft/client/input/MouseButtonEvent;DD)Z
      28: ireturn
      29: iconst_0
      30: ireturn

  public boolean hasClickedOutside(double, double, int, int, int, int);
    Code:
       0: aload_0
       1: invokevirtual #358                // Method isVisible:()Z
       4: ifne          9
       7: iconst_1
       8: ireturn
       9: dload_1
      10: iload         5
      12: i2d
      13: dcmpg
      14: iflt          47
      17: dload_3
      18: iload         6
      20: i2d
      21: dcmpg
      22: iflt          47
      25: dload_1
      26: iload         5
      28: iload         7
      30: iadd
      31: i2d
      32: dcmpl
      33: ifge          47
      36: dload_3
      37: iload         6
      39: iload         8
      41: iadd
      42: i2d
      43: dcmpl
      44: iflt          51
      47: iconst_1
      48: goto          52
      51: iconst_0
      52: istore        9
      54: iload         5
      56: sipush        147
      59: isub
      60: i2d
      61: dload_1
      62: dcmpg
      63: ifge          97
      66: dload_1
      67: iload         5
      69: i2d
      70: dcmpg
      71: ifge          97
      74: iload         6
      76: i2d
      77: dload_3
      78: dcmpg
      79: ifge          97
      82: dload_3
      83: iload         6
      85: iload         8
      87: iadd
      88: i2d
      89: dcmpg
      90: ifge          97
      93: iconst_1
      94: goto          98
      97: iconst_0
      98: istore        10
     100: iload         9
     102: ifeq          124
     105: iload         10
     107: ifne          124
     110: aload_0
     111: getfield      #314                // Field selectedTab:Lnet/minecraft/client/gui/screens/recipebook/RecipeBookTabButton;
     114: invokevirtual #632                // Method net/minecraft/client/gui/screens/recipebook/RecipeBookTabButton.isHoveredOrFocused:()Z
     117: ifne          124
     120: iconst_1
     121: goto          125
     124: iconst_0
     125: ireturn

  public boolean keyPressed(net.minecraft.client.input.KeyEvent);
    Code:
       0: aload_0
       1: iconst_0
       2: putfield      #635                // Field ignoreTextInput:Z
       5: aload_0
       6: invokevirtual #358                // Method isVisible:()Z
       9: ifeq          25
      12: aload_0
      13: getfield      #63                 // Field minecraft:Lnet/minecraft/client/Minecraft;
      16: getfield      #78                 // Field net/minecraft/client/Minecraft.player:Lnet/minecraft/client/player/LocalPlayer;
      19: invokevirtual #528                // Method net/minecraft/client/player/LocalPlayer.isSpectator:()Z
      22: ifeq          27
      25: iconst_0
      26: ireturn
      27: aload_1
      28: invokevirtual #638                // Method net/minecraft/client/input/KeyEvent.isEscape:()Z
      31: ifeq          48
      34: aload_0
      35: invokevirtual #559                // Method isOffsetNextToMainGUI:()Z
      38: ifne          48
      41: aload_0
      42: iconst_0
      43: invokevirtual #361                // Method setVisible:(Z)V
      46: iconst_1
      47: ireturn
      48: aload_0
      49: getfield      #141                // Field searchBox:Lnet/minecraft/client/gui/components/EditBox;
      52: aload_1
      53: invokevirtual #643                // Method net/minecraft/client/gui/components/EditBox.keyPressed:(Lnet/minecraft/client/input/KeyEvent;)Z
      56: ifeq          65
      59: aload_0
      60: invokevirtual #647                // Method checkSearchStringUpdate:()V
      63: iconst_1
      64: ireturn
      65: aload_0
      66: getfield      #141                // Field searchBox:Lnet/minecraft/client/gui/components/EditBox;
      69: invokevirtual #587                // Method net/minecraft/client/gui/components/EditBox.isFocused:()Z
      72: ifeq          94
      75: aload_0
      76: getfield      #141                // Field searchBox:Lnet/minecraft/client/gui/components/EditBox;
      79: invokevirtual #650                // Method net/minecraft/client/gui/components/EditBox.isVisible:()Z
      82: ifeq          94
      85: aload_1
      86: invokevirtual #638                // Method net/minecraft/client/input/KeyEvent.isEscape:()Z
      89: ifne          94
      92: iconst_1
      93: ireturn
      94: aload_0
      95: getfield      #63                 // Field minecraft:Lnet/minecraft/client/Minecraft;
      98: getfield      #651                // Field net/minecraft/client/Minecraft.options:Lnet/minecraft/client/Options;
     101: getfield      #655                // Field net/minecraft/client/Options.keyChat:Lnet/minecraft/client/KeyMapping;
     104: aload_1
     105: invokevirtual #661                // Method net/minecraft/client/KeyMapping.matches:(Lnet/minecraft/client/input/KeyEvent;)Z
     108: ifeq          136
     111: aload_0
     112: getfield      #141                // Field searchBox:Lnet/minecraft/client/gui/components/EditBox;
     115: invokevirtual #587                // Method net/minecraft/client/gui/components/EditBox.isFocused:()Z
     118: ifne          136
     121: aload_0
     122: iconst_1
     123: putfield      #635                // Field ignoreTextInput:Z
     126: aload_0
     127: getfield      #141                // Field searchBox:Lnet/minecraft/client/gui/components/EditBox;
     130: iconst_1
     131: invokevirtual #582                // Method net/minecraft/client/gui/components/EditBox.setFocused:(Z)V
     134: iconst_1
     135: ireturn
     136: aload_1
     137: invokevirtual #666                // Method net/minecraft/client/input/KeyEvent.isSelection:()Z
     140: ifeq          183
     143: aload_0
     144: getfield      #552                // Field lastRecipeCollection:Lnet/minecraft/client/gui/screens/recipebook/RecipeCollection;
     147: ifnull        183
     150: aload_0
     151: getfield      #556                // Field lastRecipe:Lnet/minecraft/world/item/crafting/display/RecipeDisplayId;
     154: ifnull        183
     157: invokestatic  #669                // Method net/minecraft/client/Minecraft.getInstance:()Lnet/minecraft/client/Minecraft;
     160: invokevirtual #673                // Method net/minecraft/client/Minecraft.getSoundManager:()Lnet/minecraft/client/sounds/SoundManager;
     163: invokestatic  #677                // Method net/minecraft/client/gui/components/AbstractWidget.playButtonClickSound:(Lnet/minecraft/client/sounds/SoundManager;)V
     166: aload_0
     167: aload_0
     168: getfield      #552                // Field lastRecipeCollection:Lnet/minecraft/client/gui/screens/recipebook/RecipeCollection;
     171: aload_0
     172: getfield      #556                // Field lastRecipe:Lnet/minecraft/world/item/crafting/display/RecipeDisplayId;
     175: aload_1
     176: invokevirtual #683                // Method net/minecraft/client/input/KeyEvent.hasShiftDown:()Z
     179: invokevirtual #548                // Method tryPlaceRecipe:(Lnet/minecraft/client/gui/screens/recipebook/RecipeCollection;Lnet/minecraft/world/item/crafting/display/RecipeDisplayId;Z)Z
     182: ireturn
     183: iconst_0
     184: ireturn

  public boolean keyReleased(net.minecraft.client.input.KeyEvent);
    Code:
       0: aload_0
       1: iconst_0
       2: putfield      #635                // Field ignoreTextInput:Z
       5: aload_0
       6: aload_1
       7: invokespecial #684                // InterfaceMethod net/minecraft/client/gui/components/events/GuiEventListener.keyReleased:(Lnet/minecraft/client/input/KeyEvent;)Z
      10: ireturn

  public boolean charTyped(net.minecraft.client.input.CharacterEvent);
    Code:
       0: aload_0
       1: getfield      #635                // Field ignoreTextInput:Z
       4: ifeq          9
       7: iconst_0
       8: ireturn
       9: aload_0
      10: invokevirtual #358                // Method isVisible:()Z
      13: ifeq          29
      16: aload_0
      17: getfield      #63                 // Field minecraft:Lnet/minecraft/client/Minecraft;
      20: getfield      #78                 // Field net/minecraft/client/Minecraft.player:Lnet/minecraft/client/player/LocalPlayer;
      23: invokevirtual #528                // Method net/minecraft/client/player/LocalPlayer.isSpectator:()Z
      26: ifeq          31
      29: iconst_0
      30: ireturn
      31: aload_0
      32: getfield      #141                // Field searchBox:Lnet/minecraft/client/gui/components/EditBox;
      35: aload_1
      36: invokevirtual #689                // Method net/minecraft/client/gui/components/EditBox.charTyped:(Lnet/minecraft/client/input/CharacterEvent;)Z
      39: ifeq          48
      42: aload_0
      43: invokevirtual #647                // Method checkSearchStringUpdate:()V
      46: iconst_1
      47: ireturn
      48: aload_0
      49: aload_1
      50: invokespecial #693                // InterfaceMethod net/minecraft/client/gui/components/events/GuiEventListener.charTyped:(Lnet/minecraft/client/input/CharacterEvent;)Z
      53: ireturn

  public boolean preeditUpdated(net.minecraft.client.input.PreeditEvent);
    Code:
       0: aload_0
       1: getfield      #635                // Field ignoreTextInput:Z
       4: ifeq          9
       7: iconst_0
       8: ireturn
       9: aload_0
      10: invokevirtual #358                // Method isVisible:()Z
      13: ifeq          29
      16: aload_0
      17: getfield      #63                 // Field minecraft:Lnet/minecraft/client/Minecraft;
      20: getfield      #78                 // Field net/minecraft/client/Minecraft.player:Lnet/minecraft/client/player/LocalPlayer;
      23: invokevirtual #528                // Method net/minecraft/client/player/LocalPlayer.isSpectator:()Z
      26: ifeq          31
      29: iconst_0
      30: ireturn
      31: aload_0
      32: getfield      #141                // Field searchBox:Lnet/minecraft/client/gui/components/EditBox;
      35: aload_1
      36: invokevirtual #694                // Method net/minecraft/client/gui/components/EditBox.preeditUpdated:(Lnet/minecraft/client/input/PreeditEvent;)Z
      39: ifeq          44
      42: iconst_1
      43: ireturn
      44: aload_0
      45: aload_1
      46: invokespecial #698                // InterfaceMethod net/minecraft/client/gui/components/events/GuiEventListener.preeditUpdated:(Lnet/minecraft/client/input/PreeditEvent;)Z
      49: ireturn

  public boolean isMouseOver(double, double);
    Code:
       0: iconst_0
       1: ireturn

  public void setFocused(boolean);
    Code:
       0: return

  public boolean isFocused();
    Code:
       0: iconst_0
       1: ireturn

  public void recipesUpdated();
    Code:
       0: aload_0
       1: invokevirtual #348                // Method selectMatchingRecipes:()V
       4: aload_0
       5: aload_0
       6: invokevirtual #117                // Method isFiltering:()Z
       9: invokevirtual #351                // Method updateTabs:(Z)V
      12: aload_0
      13: invokevirtual #358                // Method isVisible:()Z
      16: ifeq          28
      19: aload_0
      20: iconst_0
      21: aload_0
      22: invokevirtual #117                // Method isFiltering:()Z
      25: invokevirtual #354                // Method updateCollections:(ZZ)V
      28: return

  public void recipeShown(net.minecraft.world.item.crafting.display.RecipeDisplayId);
    Code:
       0: aload_0
       1: getfield      #63                 // Field minecraft:Lnet/minecraft/client/Minecraft;
       4: getfield      #78                 // Field net/minecraft/client/Minecraft.player:Lnet/minecraft/client/player/LocalPlayer;
       7: aload_1
       8: invokevirtual #733                // Method net/minecraft/client/player/LocalPlayer.removeRecipeHighlight:(Lnet/minecraft/world/item/crafting/display/RecipeDisplayId;)V
      11: return

  public void fillGhostRecipe(net.minecraft.world.item.crafting.display.RecipeDisplay);
    Code:
       0: aload_0
       1: getfield      #48                 // Field ghostSlots:Lnet/minecraft/client/gui/screens/recipebook/GhostSlots;
       4: invokevirtual #390                // Method net/minecraft/client/gui/screens/recipebook/GhostSlots.clear:()V
       7: aload_0
       8: getfield      #63                 // Field minecraft:Lnet/minecraft/client/Minecraft;
      11: getfield      #737                // Field net/minecraft/client/Minecraft.level:Lnet/minecraft/client/multiplayer/ClientLevel;
      14: invokestatic  #155                // Method java/util/Objects.requireNonNull:(Ljava/lang/Object;)Ljava/lang/Object;
      17: checkcast     #741                // class net/minecraft/world/level/Level
      20: invokestatic  #743                // Method net/minecraft/world/item/crafting/display/SlotDisplayContext.fromLevel:(Lnet/minecraft/world/level/Level;)Lnet/minecraft/util/context/ContextMap;
      23: astore_2
      24: aload_0
      25: aload_0
      26: getfield      #48                 // Field ghostSlots:Lnet/minecraft/client/gui/screens/recipebook/GhostSlots;
      29: aload_1
      30: aload_2
      31: invokevirtual #749                // Method fillGhostRecipe:(Lnet/minecraft/client/gui/screens/recipebook/GhostSlots;Lnet/minecraft/world/item/crafting/display/RecipeDisplay;Lnet/minecraft/util/context/ContextMap;)V
      34: return

  protected abstract void fillGhostRecipe(net.minecraft.client.gui.screens.recipebook.GhostSlots, net.minecraft.world.item.crafting.display.RecipeDisplay, net.minecraft.util.context.ContextMap);

  protected void sendUpdateSettings();
    Code:
       0: aload_0
       1: getfield      #63                 // Field minecraft:Lnet/minecraft/client/Minecraft;
       4: invokevirtual #425                // Method net/minecraft/client/Minecraft.getConnection:()Lnet/minecraft/client/multiplayer/ClientPacketListener;
       7: ifnull        62
      10: aload_0
      11: getfield      #32                 // Field menu:Lnet/minecraft/world/inventory/RecipeBookMenu;
      14: invokevirtual #362                // Method net/minecraft/world/inventory/RecipeBookMenu.getRecipeBookType:()Lnet/minecraft/world/inventory/RecipeBookType;
      17: astore_1
      18: aload_0
      19: getfield      #90                 // Field book:Lnet/minecraft/client/ClientRecipeBook;
      22: invokevirtual #753                // Method net/minecraft/client/ClientRecipeBook.getBookSettings:()Lnet/minecraft/stats/RecipeBookSettings;
      25: aload_1
      26: invokevirtual #757                // Method net/minecraft/stats/RecipeBookSettings.isOpen:(Lnet/minecraft/world/inventory/RecipeBookType;)Z
      29: istore_2
      30: aload_0
      31: getfield      #90                 // Field book:Lnet/minecraft/client/ClientRecipeBook;
      34: invokevirtual #753                // Method net/minecraft/client/ClientRecipeBook.getBookSettings:()Lnet/minecraft/stats/RecipeBookSettings;
      37: aload_1
      38: invokevirtual #760                // Method net/minecraft/stats/RecipeBookSettings.isFiltering:(Lnet/minecraft/world/inventory/RecipeBookType;)Z
      41: istore_3
      42: aload_0
      43: getfield      #63                 // Field minecraft:Lnet/minecraft/client/Minecraft;
      46: invokevirtual #425                // Method net/minecraft/client/Minecraft.getConnection:()Lnet/minecraft/client/multiplayer/ClientPacketListener;
      49: new           #761                // class net/minecraft/network/protocol/game/ServerboundRecipeBookChangeSettingsPacket
      52: dup
      53: aload_1
      54: iload_2
      55: iload_3
      56: invokespecial #763                // Method net/minecraft/network/protocol/game/ServerboundRecipeBookChangeSettingsPacket."<init>":(Lnet/minecraft/world/inventory/RecipeBookType;ZZ)V
      59: invokevirtual #766                // Method net/minecraft/client/multiplayer/ClientPacketListener.send:(Lnet/minecraft/network/protocol/Packet;)V
      62: return

  public net.minecraft.client.gui.narration.NarratableEntry$NarrationPriority narrationPriority();
    Code:
       0: aload_0
       1: getfield      #111                // Field visible:Z
       4: ifeq          13
       7: getstatic     #770                // Field net/minecraft/client/gui/narration/NarratableEntry$NarrationPriority.HOVERED:Lnet/minecraft/client/gui/narration/NarratableEntry$NarrationPriority;
      10: goto          16
      13: getstatic     #776                // Field net/minecraft/client/gui/narration/NarratableEntry$NarrationPriority.NONE:Lnet/minecraft/client/gui/narration/NarratableEntry$NarrationPriority;
      16: areturn

  public void updateNarration(net.minecraft.client.gui.narration.NarrationElementOutput);
    Code:
       0: invokestatic  #7                  // Method com/google/common/collect/Lists.newArrayList:()Ljava/util/ArrayList;
       3: astore_2
       4: aload_0
       5: getfield      #59                 // Field recipeBookPage:Lnet/minecraft/client/gui/screens/recipebook/RecipeBookPage;
       8: aload_2
       9: invokedynamic #779,  0            // InvokeDynamic #9:accept:(Ljava/util/List;)Ljava/util/function/Consumer;
      14: invokevirtual #783                // Method net/minecraft/client/gui/screens/recipebook/RecipeBookPage.listButtons:(Ljava/util/function/Consumer;)V
      17: aload_2
      18: aload_0
      19: getfield      #141                // Field searchBox:Lnet/minecraft/client/gui/components/EditBox;
      22: invokeinterface #310,  2          // InterfaceMethod java/util/List.add:(Ljava/lang/Object;)Z
      27: pop
      28: aload_2
      29: aload_0
      30: getfield      #279                // Field filterButton:Lnet/minecraft/client/gui/components/CycleButton;
      33: invokeinterface #310,  2          // InterfaceMethod java/util/List.add:(Ljava/lang/Object;)Z
      38: pop
      39: aload_2
      40: aload_0
      41: getfield      #13                 // Field tabButtons:Ljava/util/List;
      44: invokeinterface #787,  2          // InterfaceMethod java/util/List.addAll:(Ljava/util/Collection;)Z
      49: pop
      50: aload_2
      51: aconst_null
      52: invokestatic  #791                // Method net/minecraft/client/gui/screens/Screen.findNarratableWidget:(Ljava/util/List;Lnet/minecraft/client/gui/narration/NarratableEntry;)Lnet/minecraft/client/gui/screens/Screen$NarratableSearchResult;
      55: astore_3
      56: aload_3
      57: ifnull        75
      60: aload_3
      61: invokevirtual #797                // Method net/minecraft/client/gui/screens/Screen$NarratableSearchResult.entry:()Lnet/minecraft/client/gui/narration/NarratableEntry;
      64: aload_1
      65: invokeinterface #803,  1          // InterfaceMethod net/minecraft/client/gui/narration/NarrationElementOutput.nest:()Lnet/minecraft/client/gui/narration/NarrationElementOutput;
      70: invokeinterface #809,  2          // InterfaceMethod net/minecraft/client/gui/narration/NarratableEntry.updateNarration:(Lnet/minecraft/client/gui/narration/NarrationElementOutput;)V
      75: return

  static {};
    Code:
       0: new           #846                // class net/minecraft/client/gui/components/WidgetSprites
       3: dup
       4: ldc_w         #859                // String recipe_book/button
       7: invokestatic  #861                // Method net/minecraft/resources/Identifier.withDefaultNamespace:(Ljava/lang/String;)Lnet/minecraft/resources/Identifier;
      10: ldc_w         #867                // String recipe_book/button_highlighted
      13: invokestatic  #861                // Method net/minecraft/resources/Identifier.withDefaultNamespace:(Ljava/lang/String;)Lnet/minecraft/resources/Identifier;
      16: invokespecial #869                // Method net/minecraft/client/gui/components/WidgetSprites."<init>":(Lnet/minecraft/resources/Identifier;Lnet/minecraft/resources/Identifier;)V
      19: putstatic     #872                // Field RECIPE_BUTTON_SPRITES:Lnet/minecraft/client/gui/components/WidgetSprites;
      22: ldc_w         #876                // String textures/gui/recipe_book.png
      25: invokestatic  #861                // Method net/minecraft/resources/Identifier.withDefaultNamespace:(Ljava/lang/String;)Lnet/minecraft/resources/Identifier;
      28: putstatic     #499                // Field RECIPE_BOOK_LOCATION:Lnet/minecraft/resources/Identifier;
      31: ldc_w         #878                // String gui.recipebook.search_hint
      34: invokestatic  #163                // InterfaceMethod net/minecraft/network/chat/Component.translatable:(Ljava/lang/String;)Lnet/minecraft/network/chat/MutableComponent;
      37: getstatic     #880                // Field net/minecraft/client/gui/components/EditBox.SEARCH_HINT_STYLE:Lnet/minecraft/network/chat/Style;
      40: invokevirtual #884                // Method net/minecraft/network/chat/MutableComponent.withStyle:(Lnet/minecraft/network/chat/Style;)Lnet/minecraft/network/chat/MutableComponent;
      43: putstatic     #189                // Field SEARCH_HINT:Lnet/minecraft/network/chat/Component;
      46: ldc_w         #890                // String gui.recipebook.toggleRecipes.all
      49: invokestatic  #163                // InterfaceMethod net/minecraft/network/chat/Component.translatable:(Ljava/lang/String;)Lnet/minecraft/network/chat/MutableComponent;
      52: putstatic     #230                // Field ALL_RECIPES_TOOLTIP:Lnet/minecraft/network/chat/Component;
      55: return
}
